evlib/__init__.py
evlib/_version.py
evlib/codec/__init__.py
evlib/codec/block_access.py
evlib/codec/fileformat/__init__.py
evlib/codec/fileformat/_block_access.py
evlib/codec/fileformat/_iterator_access.py
evlib/codec/fileformat/aedat.py
evlib/codec/fileformat/conversion.py
evlib/codec/fileformat/evk.py
evlib/codec/fileformat/hdf5.py
evlib/codec/fileformat/npy.py
evlib/codec/fileformat/text.py
evlib/codec/iterator_access.py
evlib/constant.py
evlib/preproc/__init__.py
evlib/preproc/hot_pixel.py
evlib/processing/__init__.py
evlib/processing/reconstruction/__init__.py
evlib/processing/reconstruction/e2vid.py
evlib/processing/reconstruction/e2vid_module/__init__.py
evlib/processing/reconstruction/e2vid_module/base_model.py
evlib/processing/reconstruction/e2vid_module/image_reconstructor.py
evlib/processing/reconstruction/e2vid_module/model/__init__.py
evlib/processing/reconstruction/e2vid_module/model/model.py
evlib/processing/reconstruction/e2vid_module/model/submodules.py
evlib/processing/reconstruction/e2vid_module/model/unet.py
evlib/processing/reconstruction/e2vid_module/utils/__init__.py
evlib/processing/reconstruction/e2vid_module/utils/inference_utils.py
evlib/processing/reconstruction/e2vid_module/utils/loading_utils.py
evlib/py.typed
evlib/representation/__init__.py
evlib/representation/histogram.py
evlib/representation/time_map.py
evlib/representation/voxel_grid.py
evlib/types/__init__.py
evlib/types/raw_event.py
evlib/types/raw_events.py
evlib/utils/__init__.py
evlib/utils/basics.py
evlib/version.py
evlib/vis/__init__.py
evlib/vis/utils.py
evlib/vis/view2d.py
event_vision_library-0.0.1.dist-info/LICENSE
event_vision_library-0.0.1.dist-info/METADATA
event_vision_library-0.0.1.dist-info/WHEEL
event_vision_library-0.0.1.dist-info/entry_points.txt
event_vision_library-0.0.1.dist-info/RECORD
