Metadata-Version: 2.1
Name: event-vision-library
Version: 0.0.1
Summary: Event Vision Library
Home-page: https://github.com/shiba24/event-vision-library
License: MIT
Author: Shintaro Shiba
Author-email: shiba.shintaro@gmail.com
Maintainer: Shintaro Shiba
Maintainer-email: shiba.shintaro@gmail.com
Requires-Python: >=3.7,<3.11
Classifier: Development Status :: 2 - Pre-Alpha
Classifier: License :: OSI Approved :: MIT License
Classifier: Programming Language :: Python :: 3
Classifier: Programming Language :: Python :: 3.7
Classifier: Programming Language :: Python :: 3.8
Classifier: Programming Language :: Python :: 3.9
Classifier: Programming Language :: Python :: 3.10
Requires-Dist: click (>=8.0.1)
Requires-Dist: dv (>=1.0.11)
Requires-Dist: expelliarmus (>=1.1.12)
Requires-Dist: h5py (>=3.2)
Requires-Dist: matplotlib (>=3.5.3)
Requires-Dist: numpy (>=1.21.2)
Requires-Dist: opencv-python (>=4.6)
Requires-Dist: pillow (>=9.5.0)
Requires-Dist: scipy (<=1.9.1) ; python_version == "3.7"
Requires-Dist: scipy (==1.9.1) ; python_version >= "3.8" and python_version < "3.11"
Requires-Dist: torch (<=2.0.0) ; python_version == "3.7"
Requires-Dist: torch (>=2.0.0) ; python_version >= "3.8" and python_version < "3.11"
Requires-Dist: wheel (>=0.38.4)
Project-URL: Changelog, https://github.com/shiba24/event-vision-library/releases
Project-URL: Documentation, https://event-vision-library.readthedocs.io
Project-URL: Repository, https://github.com/shiba24/event-vision-library
